{"hasFailed":false,"conjuncts":"check(dad, bedroom, T2, T3)","children":[{"hasFailed":false,"conjuncts":"occurs(light(bedroom, on), T2, T2),occurs(goto(dad, bedroom), T2, T3)","children":[{"hasFailed":false,"conjuncts":"occurs(goto(dad, bedroom), 1, T3)"},{"hasFailed":false,"conjuncts":"occurs(goto(dad, bedroom), 1, T3)"},{"hasFailed":false,"conjuncts":"occurs(goto(dad, bedroom), 2, T3)"},{"hasFailed":false,"conjuncts":"occurs(goto(dad, bedroom), 2, T3)"},{"hasFailed":false,"conjuncts":"occurs(goto(dad, bedroom), 3, T3)"},{"hasFailed":false,"conjuncts":"occurs(goto(dad, bedroom), 3, T3)"},{"hasFailed":false,"conjuncts":"occurs(goto(dad, bedroom), 4, T3)"}]},{"hasFailed":false,"conjuncts":"occurs(light(bedroom, off), T, T)"}]}